{".class": "MypyFile", "_fullname": "distutils.util", "is_partial_stub_package": false, "is_stub": true, "names": {".class": "SymbolTable", "Any": {".class": "SymbolTableNode", "cross_ref": "typing.Any", "kind": "Gdef", "module_hidden": true, "module_public": false}, "Callable": {".class": "SymbolTableNode", "cross_ref": "typing.Callable", "kind": "Gdef", "module_hidden": true, "module_public": false}, "List": {".class": "SymbolTableNode", "cross_ref": "typing.List", "kind": "Gdef", "module_hidden": true, "module_public": false}, "Mapping": {".class": "SymbolTableNode", "cross_ref": "typing.Mapping", "kind": "Gdef", "module_hidden": true, "module_public": false}, "Optional": {".class": "SymbolTableNode", "cross_ref": "typing.Optional", "kind": "Gdef", "module_hidden": true, "module_public": false}, "Tuple": {".class": "SymbolTableNode", "cross_ref": "typing.Tuple", "kind": "Gdef", "module_hidden": true, "module_public": false}, "__doc__": {".class": "SymbolTableNode", "kind": "Gdef", "node": {".class": "Var", "flags": ["is_ready"], "fullname": "distutils.util.__doc__", "name": "__doc__", "type": "builtins.str"}}, "__file__": {".class": "SymbolTableNode", "kind": "Gdef", "node": {".class": "Var", "flags": ["is_ready"], "fullname": "distutils.util.__file__", "name": "__file__", "type": "builtins.str"}}, "__name__": {".class": "SymbolTableNode", "kind": "Gdef", "node": {".class": "Var", "flags": ["is_ready"], "fullname": "distutils.util.__name__", "name": "__name__", "type": "builtins.str"}}, "__package__": {".class": "SymbolTableNode", "kind": "Gdef", "node": {".class": "Var", "flags": ["is_ready"], "fullname": "distutils.util.__package__", "name": "__package__", "type": "builtins.str"}}, "byte_compile": {".class": "SymbolTableNode", "kind": "Gdef", "node": {".class": "FuncDef", "arg_kinds": [0, 1, 1, 1, 1, 1, 1, 1], "arg_names": ["py_files", "optimize", "force", "prefix", "base_dir", "verbose", "dry_run", "direct"], "flags": [], "fullname": "distutils.util.byte_compile", "name": "byte_compile", "type": {".class": "CallableType", "arg_kinds": [0, 1, 1, 1, 1, 1, 1, 1], "arg_names": ["py_files", "optimize", "force", "prefix", "base_dir", "verbose", "dry_run", "direct"], "arg_types": [{".class": "Instance", "args": ["builtins.str"], "type_ref": "builtins.list"}, "builtins.int", "builtins.bool", {".class": "UnionType", "items": ["builtins.str", {".class": "NoneType"}]}, {".class": "UnionType", "items": ["builtins.str", {".class": "NoneType"}]}, "builtins.bool", "builtins.bool", {".class": "UnionType", "items": ["builtins.bool", {".class": "NoneType"}]}], "bound_args": [], "def_extras": {"first_arg": null}, "fallback": "builtins.function", "implicit": false, "is_ellipsis_args": false, "name": "byte_compile", "ret_type": {".class": "NoneType"}, "type_guard": null, "variables": []}}}, "change_root": {".class": "SymbolTableNode", "kind": "Gdef", "node": {".class": "FuncDef", "arg_kinds": [0, 0], "arg_names": ["new_root", "pathname"], "flags": [], "fullname": "distutils.util.change_root", "name": "change_root", "type": {".class": "CallableType", "arg_kinds": [0, 0], "arg_names": ["new_root", "pathname"], "arg_types": ["builtins.str", "builtins.str"], "bound_args": [], "def_extras": {"first_arg": null}, "fallback": "builtins.function", "implicit": false, "is_ellipsis_args": false, "name": "change_root", "ret_type": "builtins.str", "type_guard": null, "variables": []}}}, "check_environ": {".class": "SymbolTableNode", "kind": "Gdef", "node": {".class": "FuncDef", "arg_kinds": [], "arg_names": [], "flags": [], "fullname": "distutils.util.check_environ", "name": "check_environ", "type": {".class": "CallableType", "arg_kinds": [], "arg_names": [], "arg_types": [], "bound_args": [], "def_extras": {"first_arg": null}, "fallback": "builtins.function", "implicit": false, "is_ellipsis_args": false, "name": "check_environ", "ret_type": {".class": "NoneType"}, "type_guard": null, "variables": []}}}, "convert_path": {".class": "SymbolTableNode", "kind": "Gdef", "node": {".class": "FuncDef", "arg_kinds": [0], "arg_names": ["pathname"], "flags": [], "fullname": "distutils.util.convert_path", "name": "convert_path", "type": {".class": "CallableType", "arg_kinds": [0], "arg_names": ["pathname"], "arg_types": ["builtins.str"], "bound_args": [], "def_extras": {"first_arg": null}, "fallback": "builtins.function", "implicit": false, "is_ellipsis_args": false, "name": "convert_path", "ret_type": "builtins.str", "type_guard": null, "variables": []}}}, "execute": {".class": "SymbolTableNode", "kind": "Gdef", "node": {".class": "FuncDef", "arg_kinds": [0, 0, 1, 1, 1], "arg_names": ["func", "args", "msg", "verbose", "dry_run"], "flags": [], "fullname": "distutils.util.execute", "name": "execute", "type": {".class": "CallableType", "arg_kinds": [0, 0, 1, 1, 1], "arg_names": ["func", "args", "msg", "verbose", "dry_run"], "arg_types": [{".class": "CallableType", "arg_kinds": [2, 4], "arg_names": [null, null], "arg_types": [{".class": "AnyType", "missing_import_name": null, "source_any": null, "type_of_any": 2}, {".class": "AnyType", "missing_import_name": null, "source_any": null, "type_of_any": 2}], "bound_args": [], "def_extras": {}, "fallback": "builtins.function", "implicit": false, "is_ellipsis_args": true, "name": null, "ret_type": {".class": "NoneType"}, "type_guard": null, "variables": []}, {".class": "Instance", "args": [{".class": "AnyType", "missing_import_name": null, "source_any": null, "type_of_any": 2}], "type_ref": "builtins.tuple"}, {".class": "UnionType", "items": ["builtins.str", {".class": "NoneType"}]}, "builtins.bool", "builtins.bool"], "bound_args": [], "def_extras": {"first_arg": null}, "fallback": "builtins.function", "implicit": false, "is_ellipsis_args": false, "name": "execute", "ret_type": {".class": "NoneType"}, "type_guard": null, "variables": []}}}, "get_platform": {".class": "SymbolTableNode", "kind": "Gdef", "node": {".class": "FuncDef", "arg_kinds": [], "arg_names": [], "flags": [], "fullname": "distutils.util.get_platform", "name": "get_platform", "type": {".class": "CallableType", "arg_kinds": [], "arg_names": [], "arg_types": [], "bound_args": [], "def_extras": {"first_arg": null}, "fallback": "builtins.function", "implicit": false, "is_ellipsis_args": false, "name": "get_platform", "ret_type": "builtins.str", "type_guard": null, "variables": []}}}, "rfc822_escape": {".class": "SymbolTableNode", "kind": "Gdef", "node": {".class": "FuncDef", "arg_kinds": [0], "arg_names": ["header"], "flags": [], "fullname": "distutils.util.rfc822_escape", "name": "rfc822_escape", "type": {".class": "CallableType", "arg_kinds": [0], "arg_names": ["header"], "arg_types": ["builtins.str"], "bound_args": [], "def_extras": {"first_arg": null}, "fallback": "builtins.function", "implicit": false, "is_ellipsis_args": false, "name": "rfc822_escape", "ret_type": "builtins.str", "type_guard": null, "variables": []}}}, "split_quoted": {".class": "SymbolTableNode", "kind": "Gdef", "node": {".class": "FuncDef", "arg_kinds": [0], "arg_names": ["s"], "flags": [], "fullname": "distutils.util.split_quoted", "name": "split_quoted", "type": {".class": "CallableType", "arg_kinds": [0], "arg_names": ["s"], "arg_types": ["builtins.str"], "bound_args": [], "def_extras": {"first_arg": null}, "fallback": "builtins.function", "implicit": false, "is_ellipsis_args": false, "name": "split_quoted", "ret_type": {".class": "Instance", "args": ["builtins.str"], "type_ref": "builtins.list"}, "type_guard": null, "variables": []}}}, "strtobool": {".class": "SymbolTableNode", "kind": "Gdef", "node": {".class": "FuncDef", "arg_kinds": [0], "arg_names": ["val"], "flags": [], "fullname": "distutils.util.strtobool", "name": "strtobool", "type": {".class": "CallableType", "arg_kinds": [0], "arg_names": ["val"], "arg_types": ["builtins.str"], "bound_args": [], "def_extras": {"first_arg": null}, "fallback": "builtins.function", "implicit": false, "is_ellipsis_args": false, "name": "strtobool", "ret_type": "builtins.bool", "type_guard": null, "variables": []}}}, "subst_vars": {".class": "SymbolTableNode", "kind": "Gdef", "node": {".class": "FuncDef", "arg_kinds": [0, 0], "arg_names": ["s", "local_vars"], "flags": [], "fullname": "distutils.util.subst_vars", "name": "subst_vars", "type": {".class": "CallableType", "arg_kinds": [0, 0], "arg_names": ["s", "local_vars"], "arg_types": ["builtins.str", {".class": "Instance", "args": ["builtins.str", "builtins.str"], "type_ref": "typing.Mapping"}], "bound_args": [], "def_extras": {"first_arg": null}, "fallback": "builtins.function", "implicit": false, "is_ellipsis_args": false, "name": "subst_vars", "ret_type": {".class": "NoneType"}, "type_guard": null, "variables": []}}}}, "path": "/Users/max/.cache/pre-commit/repoejng1phv/py_env-python3.7/lib/python3.7/site-packages/mypy/typeshed/stdlib/distutils/util.pyi"}