{"data_mtime":1686785215,"dep_lines":[6,1,2,5,3,1,1,1,1,1,1,1],"dep_prios":[5,5,5,5,5,5,30,30,30,30,30,30],"dependencies":["urllib3.util.retry","email.errors","http.client","urllib3.connectionpool","typing","builtins","abc","email","http","io","urllib3.response","urllib3.util"],"hash":"f658b2edf809d9d785f3f23192b41e9e2ec1c3494c75bf5d3ad6393aeaa60604","id":"urllib3.exceptions","ignore_all":true,"interface_hash":"bbf6b84d86cc1cf70ed90a5d6474abcfe385de64ece88ae64fbe4e147c626651","mtime":1686357226,"options":{"allow_redefinition":false,"allow_untyped_globals":false,"always_false":[],"always_true":[],"bazel":false,"check_untyped_defs":true,"disable_bytearray_promotion":false,"disable_error_code":[],"disable_memoryview_promotion":false,"disabled_error_codes":[],"disallow_any_decorated":false,"disallow_any_explicit":false,"disallow_any_expr":false,"disallow_any_generics":true,"disallow_any_unimported":false,"disallow_incomplete_defs":false,"disallow_subclassing_any":false,"disallow_untyped_calls":true,"disallow_untyped_decorators":false,"disallow_untyped_defs":true,"enable_error_code":[],"enabled_error_codes":[],"follow_imports":"normal","follow_imports_for_stubs":false,"ignore_errors":false,"ignore_missing_imports":true,"implicit_optional":false,"implicit_reexport":true,"local_partial_types":false,"mypyc":false,"platform":"darwin","plugins":[],"strict_concatenate":false,"strict_equality":false,"strict_optional":true,"warn_no_return":true,"warn_return_any":false,"warn_unreachable":false,"warn_unused_ignores":true},"path":"/Users/max/.cache/pre-commit/repoqeruopqx/py_env-python3.9/lib/python3.9/site-packages/urllib3-stubs/exceptions.pyi","plugin_data":null,"size":2947,"suppressed":[],"version_id":"1.3.0"}